torchlite/__init__.py
torchlite/data/__init__.py
torchlite/data/fetcher.py
torchlite/data/files.py
torchlite/data/datasets/__init__.py
torchlite/data/datasets/samplers.py
torchlite/data/datasets/srpgan.py
torchlite/eval/__init__.py
torchlite/matplotlib/__init__.py
torchlite/matplotlib/models_plot.py
torchlite/matplotlib/utils.py
torchlite/pandas/__init__.py
torchlite/pandas/cleaner.py
torchlite/pandas/date.py
torchlite/pandas/merger.py
torchlite/pandas/splitter.py
torchlite/pandas/tabular_encoder.py
torchlite/pandas/time_series.py
torchlite/pandas/tools.py
torchlite/spark/__init__.py
torchlite/tf/__init__.py
torchlite/torch/__init__.py
torchlite/torch/layers.py
torchlite/torch/shortcuts.py
torchlite/torch/test_callbacks.py
torchlite/torch/train_callbacks.py
torchlite/torch/transforms.py
torchlite/torch/learner/__init__.py
torchlite/torch/learner/cores.py
torchlite/torch/losses/__init__.py
torchlite/torch/losses/srpgan.py
torchlite/torch/metrics/__init__.py
torchlite/torch/models/__init__.py
torchlite/torch/models/srpgan.py
torchlite/torch/tools/__init__.py
torchlite/torch/tools/image_tools.py
torchlite/torch/tools/pytorch_modelsize.py
torchlite/torch/tools/ssim.py
torchlite/torch/tools/tensor_tools.py
torchlite-0.2.0.1.dist-info/METADATA
torchlite-0.2.0.1.dist-info/RECORD
torchlite-0.2.0.1.dist-info/WHEEL
torchlite-0.2.0.1.dist-info/top_level.txt
