Metadata-Version: 2.1
Name: torchlite
Version: 0.2.0.1
Summary: A high level library on top of machine learning frameworks
Home-page: https://github.com/EKami/Torchlite
Author: GODARD Tuatini
Author-email: tuatinigodard@gmail.com
License: MIT
Keywords: development
Platform: UNKNOWN
Classifier: Development Status :: 3 - Alpha
Classifier: Intended Audience :: Developers
Classifier: Topic :: Software Development :: Build Tools
Classifier: License :: OSI Approved :: MIT License
Classifier: Programming Language :: Python :: 3.4
Classifier: Programming Language :: Python :: 3.5
Classifier: Programming Language :: Python :: 3.6
Requires-Dist: isoweek
Requires-Dist: tqdm
Requires-Dist: bcolz
Requires-Dist: kaggle-data
Requires-Dist: opencv-python
Requires-Dist: torch
Requires-Dist: torchvision
Requires-Dist: tensorflow-gpu
Requires-Dist: scikit-image
Requires-Dist: setuptools
Requires-Dist: numpy
Requires-Dist: matplotlib
Requires-Dist: scipy
Requires-Dist: Pillow
Requires-Dist: scikit-learn
Requires-Dist: tensorboardX
Requires-Dist: typing
Requires-Dist: PyYAML
Requires-Dist: Augmentor
Requires-Dist: feather-format
Requires-Dist: fuzzywuzzy
Requires-Dist: python-Levenshtein
Requires-Dist: category-encoders
Requires-Dist: torchlite
